oandabase/__init__.py
oandabase/oanda.py
oandabase-0.1.0.dist-info/LICENSE
oandabase-0.1.0.dist-info/METADATA
oandabase-0.1.0.dist-info/WHEEL
oandabase-0.1.0.dist-info/top_level.txt
oandabase-0.1.0.dist-info/RECORD
