Metadata-Version: 2.1
Name: oandabase
Version: 0.1.0
Summary: Oanda account connection, order sending and data feed
Home-page: https://github.com/ant358/oanda-base/
Author: Anthony Wynne
Author-email: 12174019+ant358@users.noreply.github.com
License: UNKNOWN
Project-URL: Bug Tracker, https://github.com/ant358/oanda-base/issues
Platform: UNKNOWN
Classifier: Programming Language :: Python :: 3
Classifier: License :: OSI Approved :: BSD License
Classifier: Operating System :: OS Independent
Requires-Python: >=3.7
License-File: LICENSE
Requires-Dist: python-decouple (==3.4)
Requires-Dist: requests (==2.25.1)
